[
    {
        "Date": 1711411200000,
        "Description": "חומוס חמודות",
        "Amount": 28.0,
        "Flag": [
            "Leisure"
        ]
    },
    {
        "Date": 1711584000000,
        "Description": "סופר מימון",
        "Amount": 8.0,
        "Flag": [
            "Leisure"
        ]
    },
    {
        "Date": 1711756800000,
        "Description": "פיצה ציז מודיעין",
        "Amount": 25.0,
        "Flag": [
            "Leisure"
        ]
    },
    {
        "Date": 1711843200000,
        "Description": "סופר אלונית -אלון המ",
        "Amount": 9.9,
        "Flag": [
            "Leisure"
        ]
    }
]